SnB_input_files/castep.param
SnB_input_files/cp2k_input.inp
SnB_input_files/default_POTCARs.yaml
SnB_input_files/example_generate_all_config.yaml
SnB_input_files/example_generate_config.yaml
SnB_input_files/incar.yaml
SnB_input_files/qe_input.yaml
fonts/Montserrat-Regular.ttf
shakenbreak/__init__.py
shakenbreak/analysis.py
shakenbreak/cli.py
shakenbreak/distortions.py
shakenbreak/energy_lowering_distortions.py
shakenbreak/input.py
shakenbreak/io.py
shakenbreak/plotting.py
shakenbreak/shakenbreak.mplstyle
shakenbreak/vasp.py
shakenbreak/__pycache__/__init__.cpython-39.pyc
shakenbreak/__pycache__/analysis.cpython-39.pyc
shakenbreak/__pycache__/cli.cpython-39.pyc
shakenbreak/__pycache__/distortions.cpython-39.pyc
shakenbreak/__pycache__/energy_lowering_distortions.cpython-39.pyc
shakenbreak/__pycache__/input.cpython-39.pyc
shakenbreak/__pycache__/io.cpython-39.pyc
shakenbreak/__pycache__/plotting.cpython-39.pyc
shakenbreak/__pycache__/vasp.cpython-39.pyc
shakenbreak/bash_scripts/SnB_run.sh
shakenbreak/bash_scripts/save_vasp_files.sh
tests/__init__.py
tests/test_analysis.py
tests/test_cli.py
tests/test_distortions.py
tests/test_energy_lowering_distortions.py
tests/test_input.py
tests/test_io.py
tests/test_local.py
tests/test_plotting.py
tests/test_shakenbreak.py
tests/data/README
tests/data/castep/POSCAR
tests/data/castep/Si2-cellopt-aniso.castep
tests/data/castep/castep_mod.param
tests/data/castep/vac_1_Cd_0/test_vac_1_Cd_0.yaml
tests/data/castep/vac_1_Cd_0/Bond_Distortion_30.0%/castep.cell
tests/data/castep/vac_1_Cd_0/Bond_Distortion_30.0%/castep.param
tests/data/castep/vac_1_Cd_0/Bond_Distortion_30.0%/castep_user_parameters.param
tests/data/castep/vac_1_Cd_0/Bond_Distortion_30.0%/geom.castep
tests/data/cp2k/POSCAR
tests/data/cp2k/cp2k.restart
tests/data/cp2k/cp2k_input_mod.inp
tests/data/cp2k/vac_1_Cd_0/test_vac_1_Cd_0.yaml
tests/data/cp2k/vac_1_Cd_0/Bond_Distortion_30.0%/cp2k_input.inp
tests/data/cp2k/vac_1_Cd_0/Bond_Distortion_30.0%/cp2k_input_user_parameters.inp
shakenbreak-24.1.7.dist-info/LICENSE
shakenbreak-24.1.7.dist-info/METADATA
shakenbreak-24.1.7.dist-info/WHEEL
shakenbreak-24.1.7.dist-info/entry_points.txt
shakenbreak-24.1.7.dist-info/top_level.txt
shakenbreak-24.1.7.dist-info/RECORD
