Metadata-Version: 2.1
Name: shakenbreak
Version: 24.1.7
Summary: Package to generate and analyse distorted defect structures, in order to identify ground-state and metastable defect configurations.
Home-page: https://shakenbreak.readthedocs.io/en/latest/index.html
Author: Irea Mosquera-Lois, Seán R. Kavanagh
Author-email: i.mosquera-lois22@imperial.ac.uk, sean.kavanagh.19@ucl.ac.uk
Maintainer: Irea Mosquera-Lois, Seán R. Kavanagh
Maintainer-email: i.mosquera-lois22@imperial.ac.uk, sean.kavanagh.19@ucl.ac.uk
License: MIT
Project-URL: Homepage, https://shakenbreak.readthedocs.io/en/latest/index.html
Project-URL: Documentation, https://shakenbreak.readthedocs.io/en/latest/index.html
Project-URL: Package, https://pypi.org/project/shakenbreak/
Project-URL: Repository, https://github.com/SMTG-UCL/shakenbreak
Keywords: chemistry pymatgen dft defects structure-searching distortions symmetry-breaking
Platform: UNKNOWN
Classifier: Development Status :: 5 - Production/Stable
Classifier: Intended Audience :: Science/Research
Classifier: License :: OSI Approved :: MIT License
Classifier: Natural Language :: English
Classifier: Programming Language :: Python :: 3 :: Only
Classifier: Programming Language :: Python :: 3.5
Classifier: Topic :: Scientific/Engineering :: Chemistry
Classifier: Topic :: Scientific/Engineering :: Physics
License-File: LICENSE
Requires-Dist: numpy
Requires-Dist: pymatgen (>=2022.10.22)
Requires-Dist: pymatgen-analysis-defects (>=2022.10.28)
Requires-Dist: matplotlib
Requires-Dist: ase
Requires-Dist: pandas (>=1.1.0)
Requires-Dist: seaborn
Requires-Dist: hiphive
Requires-Dist: monty
Requires-Dist: click (>8.0)
Requires-Dist: importlib-metadata
Provides-Extra: docs
Requires-Dist: sphinx ; extra == 'docs'
Requires-Dist: sphinx-book-theme ; extra == 'docs'
Requires-Dist: sphinx-click ; extra == 'docs'
Requires-Dist: sphinx-design ; extra == 'docs'
Provides-Extra: pdf
Requires-Dist: pycairo ; extra == 'pdf'
Provides-Extra: tests
Requires-Dist: pytest (>=7.1.3) ; extra == 'tests'
Requires-Dist: pytest-mpl (==0.15.1) ; extra == 'tests'
